{
  "steps": [
    {
      "id": "top",
      "title": "Choose a Top",
      "blurb": "Start strong—like espresso for your outfit.",
      "options": [
        {
          "id": "top-1",
          "name": "Top 1",
          "img": "assets/graphics/TOP%201.png",
          "desc": "Clean lines with an editorial edge."
        },
        {
          "id": "top-2",
          "name": "Top 2",
          "img": "assets/graphics/TOP%202.png",
          "desc": "Minimal, sharp, camera-ready."
        },
        {
          "id": "top-3",
          "name": "Top 3",
          "img": "assets/graphics/TOP%203.png",
          "desc": "Soft structure, high gloss."
        },
        {
          "id": "top-4",
          "name": "Top 4",
          "img": "assets/graphics/TOP%204%20FULL.png",
          "desc": "Statement silhouette, cover-worthy."
        }
      ],
      "dependencies": {}
    },
    {
      "id": "bottom",
      "title": "Choose a Bottom",
      "blurb": "Balance is key. Also: pockets.",
      "options": [
        {
          "id": "bottom-1",
          "name": "Bottom 1",
          "img": "assets/graphics/BOTTOMS%201.png",
          "desc": "Tailored and timeless."
        },
        {
          "id": "bottom-2",
          "name": "Bottom 2",
          "img": "assets/graphics/BOTTOMS%202.png",
          "desc": "Swishy, flirty, editor-approved."
        },
        {
          "id": "bottom-3",
          "name": "Bottom 3",
          "img": "assets/graphics/BOTTOMS%203.png",
          "desc": "Classic cut with modern attitude."
        },
        {
          "id": "bottom-4",
          "name": "Bottom 4",
          "img": "assets/graphics/BOTTOMS%204.png",
          "desc": "Slinky movement, luxe finish."
        }
      ],
      "dependencies": {}
    },
    {
      "id": "accessory",
      "title": "Choose an Accessory",
      "blurb": "The plot twist your outfit deserves.",
      "options": [
        {
          "id": "acc-1",
          "name": "Accessory 1",
          "img": "assets/graphics/ACC%201.png",
          "desc": "Hands-free polish."
        },
        {
          "id": "acc-2",
          "name": "Accessory 2",
          "img": "assets/graphics/ACC%202.png",
          "desc": "Sparkle with subtle bite."
        },
        {
          "id": "acc-3",
          "name": "Accessory 3",
          "img": "assets/graphics/ACC%203.png",
          "desc": "French-girl flourish."
        },
        {
          "id": "acc-4",
          "name": "Accessory 4",
          "img": "assets/graphics/ACC%204.png",
          "desc": "Waist-snatching statement."
        }
      ],
      "dependencies": {}
    },
    {
      "id": "jewelry",
      "title": "Choose Jewelry",
      "blurb": "Final sparkle. Main-character energy, activated.",
      "options": [
        {
          "id": "j-1",
          "name": "Gold Huggies",
          "img": "https://images.unsplash.com/photo-1522312346375-d1a52e2b99b3?w=800&q=80",
          "desc": "Delicate hoops that whisper ‘main character.’"
        },
        {
          "id": "j-2",
          "name": "Layered Necklace",
          "img": "https://images.unsplash.com/photo-1543294001-f7cd5d7fb516?w=800&q=80",
          "desc": "Stacked shine; gives neckline a promotion."
        },
        {
          "id": "j-3",
          "name": "Tennis Bracelet",
          "img": "https://images.unsplash.com/photo-1515562141207-7a88fb7ce338?w=800&q=80",
          "desc": "Classic sparkle—serves looks and aces."
        },
        {
          "id": "j-4",
          "name": "Pearl Studs",
          "img": "https://images.unsplash.com/photo-1543294001-f7cd5d7fb516?w=800&q=80",
          "desc": "Elegant, timeless, editorial cool."
        }
      ],
      "dependencies": {}
    }
  ],
  "jokes": [
    "Outfits don’t make the person—but they definitely RSVP for you.",
    "Fashion tip: if it has pockets, it’s already iconic.",
    "Warning: selections may cause mirror selfies.",
    "Shine so bright, the paparazzi file a ticket."
  ]
}